odoo10_addon_hr_expense_invoice-10.0.1.0.1-py2.7-nspkg.pth
odoo/addons/hr_expense_invoice/README.rst
odoo/addons/hr_expense_invoice/__init__.py
odoo/addons/hr_expense_invoice/__manifest__.py
odoo/addons/hr_expense_invoice/i18n/cs_CZ.po
odoo/addons/hr_expense_invoice/i18n/es.po
odoo/addons/hr_expense_invoice/i18n/fr.po
odoo/addons/hr_expense_invoice/i18n/hr.po
odoo/addons/hr_expense_invoice/i18n/hr_expense_invoice.pot
odoo/addons/hr_expense_invoice/i18n/nl_NL.po
odoo/addons/hr_expense_invoice/i18n/pt.po
odoo/addons/hr_expense_invoice/models/__init__.py
odoo/addons/hr_expense_invoice/models/hr_expense.py
odoo/addons/hr_expense_invoice/models/hr_expense_sheet.py
odoo/addons/hr_expense_invoice/static/description/icon.png
odoo/addons/hr_expense_invoice/tests/__init__.py
odoo/addons/hr_expense_invoice/tests/test_hr_expense_invoice.py
odoo/addons/hr_expense_invoice/views/hr_expense_views.xml
odoo10_addon_hr_expense_invoice-10.0.1.0.1.dist-info/METADATA
odoo10_addon_hr_expense_invoice-10.0.1.0.1.dist-info/RECORD
odoo10_addon_hr_expense_invoice-10.0.1.0.1.dist-info/WHEEL
odoo10_addon_hr_expense_invoice-10.0.1.0.1.dist-info/namespace_packages.txt
odoo10_addon_hr_expense_invoice-10.0.1.0.1.dist-info/top_level.txt
